odoo/addons/web_custom_modifier/README.rst
odoo/addons/web_custom_modifier/__init__.py
odoo/addons/web_custom_modifier/__manifest__.py
odoo/addons/web_custom_modifier/utils.py
odoo/addons/web_custom_modifier/i18n/fr.po
odoo/addons/web_custom_modifier/i18n/it.po
odoo/addons/web_custom_modifier/i18n/web_custom_modifier.pot
odoo/addons/web_custom_modifier/models/__init__.py
odoo/addons/web_custom_modifier/models/base.py
odoo/addons/web_custom_modifier/models/common.py
odoo/addons/web_custom_modifier/models/ir_ui_view.py
odoo/addons/web_custom_modifier/models/web_custom_modifier.py
odoo/addons/web_custom_modifier/readme/CONTEXT.md
odoo/addons/web_custom_modifier/readme/CONTRIBUTOR.md
odoo/addons/web_custom_modifier/readme/DESCRIPTION.md
odoo/addons/web_custom_modifier/readme/ROADMAP.md
odoo/addons/web_custom_modifier/readme/USAGE.md
odoo/addons/web_custom_modifier/security/ir.model.access.csv
odoo/addons/web_custom_modifier/static/description/button_modifier.png
odoo/addons/web_custom_modifier/static/description/contact_form_type_not_selected.png
odoo/addons/web_custom_modifier/static/description/contact_form_without_selection_item.png
odoo/addons/web_custom_modifier/static/description/custom_modifier_menu.png
odoo/addons/web_custom_modifier/static/description/custom_widget.png
odoo/addons/web_custom_modifier/static/description/excluded_groups.png
odoo/addons/web_custom_modifier/static/description/force_save_modifier.png
odoo/addons/web_custom_modifier/static/description/hide_selection_item_modifier.png
odoo/addons/web_custom_modifier/static/description/icon.png
odoo/addons/web_custom_modifier/static/description/index.html
odoo/addons/web_custom_modifier/static/description/new_custom_modifier.png
odoo/addons/web_custom_modifier/static/description/number_lines_per_page_modifier.png
odoo/addons/web_custom_modifier/static/description/optional_modifier.png
odoo/addons/web_custom_modifier/static/description/optional_modifier_applied.png
odoo14_addon_web_custom_modifier-14.0.2.0.2.dev4.dist-info/METADATA
odoo14_addon_web_custom_modifier-14.0.2.0.2.dev4.dist-info/WHEEL
odoo14_addon_web_custom_modifier-14.0.2.0.2.dev4.dist-info/top_level.txt
odoo14_addon_web_custom_modifier-14.0.2.0.2.dev4.dist-info/RECORD
