Metadata-Version: 2.1
Name: odoo14-addon-web-custom-modifier
Version: 14.0.2.0.2.dev4
Summary: Enable easily customizing view modifiers.
Home-page: https://github.com/OCA/web
Author: Numigi, Odoo Community Association (OCA)
Author-email: support@odoo-community.org
License: LGPL-3
Platform: UNKNOWN
Classifier: Programming Language :: Python
Classifier: Framework :: Odoo
Classifier: Framework :: Odoo :: 14.0
Classifier: License :: OSI Approved :: GNU Lesser General Public License v3 (LGPLv3)
Requires-Python: >=3.6
Requires-Dist: odoo <14.1dev,>=14.0a
